tictoc-0.2.0.dist-info/METADATA
tictoc-0.2.0.dist-info/WHEEL
tictoc-0.2.0.dist-info/licenses/LICENSE.md
tictoc/__init__.py
tictoc/tictoc.pypy39-pp73-darwin.so
tictoc-0.2.0.dist-info/RECORD
