Metadata-Version: 2.4
Name: tictoc
Version: 0.2.0
Classifier: Programming Language :: Rust
Classifier: Programming Language :: Python :: Implementation :: CPython
Classifier: Programming Language :: Python :: Implementation :: PyPy
Classifier: License :: OSI Approved :: MIT License
License-File: LICENSE.md
Summary: Fast, simple and accurate Python timing. Written in Rust.
Author-email: Andrew Conlin <andrew@andrewconl.in>
Requires-Python: >=3.8
Project-URL: Repository, https://git.andrewconl.in/andrew/tictoc.git
Project-URL: Changelog, https://git.andrewconl.in/andrew/tictoc/src/branch/main/CHANGELOG.md
